templates/__init__.py
templates/cli.py
templates/fastapi-backend/.env.development
templates/fastapi-backend/.env.production
templates/fastapi-backend/.env.staging
templates/fastapi-backend/.gitignore
templates/fastapi-backend/.pre-commit-config.yaml
templates/fastapi-backend/app/__init__.py
templates/fastapi-backend/app/config/__int__.py
templates/fastapi-backend/app/config/logging_config.py
templates/fastapi-backend/app/config/orjsonConfig.py
templates/fastapi-backend/app/database/__init__.py
templates/fastapi-backend/app/database/postgres/__init__.py
templates/fastapi-backend/app/database/postgres/db.py
templates/fastapi-backend/app/database/postgres/models/__init__.py
templates/fastapi-backend/app/helpers/__init__.py
templates/fastapi-backend/app/helpers/assets/__init__.py
templates/fastapi-backend/app/helpers/constants/__init__.py
templates/fastapi-backend/app/helpers/models/__init__.py
templates/fastapi-backend/app/helpers/pydantic/__init__.py
templates/fastapi-backend/app/helpers/utilities/__init__.py
templates/fastapi-backend/app/helpers/utilities/envVar.py
templates/fastapi-backend/app/helpers/utilities/get_free_cpus.py
templates/fastapi-backend/app/helpers/utilities/iso8601.py
templates/fastapi-backend/app/helpers/utilities/queue_util.py
templates/fastapi-backend/app/helpers/utilities/string.py
templates/fastapi-backend/app/internal/__init__.py
templates/fastapi-backend/app/middleware/__init__.py
templates/fastapi-backend/app/routers/__init__.py
templates/fastapi-backend/app/routers/health.py
templates/fastapi-backend/app/services/__init__.py
templates/fastapi-backend/app/static/__init__.py
templates/fastapi-backend/main.py
templates/fastapi-backend/Makefile
templates/fastapi-backend/pyproject.toml
templates/fastapi-backend/README.md
templates/fastapi-backend/watchdog.ini
smh_fastapi_backend_templates-0.1.1.dist-info/entry_points.txt
smh_fastapi_backend_templates-0.1.1.dist-info/LICENSE
smh_fastapi_backend_templates-0.1.1.dist-info/METADATA
smh_fastapi_backend_templates-0.1.1.dist-info/WHEEL
smh_fastapi_backend_templates-0.1.1.dist-info/RECORD
