Metadata-Version: 2.3
Name: smh-fastapi-backend-templates
Version: 0.1.1
Summary: A CLI tool for managing templates
Author: S MUNI HARISH
Author-email: samamuniharish@gmail.com
Requires-Python: >=3.8,<4.0
Classifier: Programming Language :: Python :: 3
Classifier: Programming Language :: Python :: 3.8
Classifier: Programming Language :: Python :: 3.9
Classifier: Programming Language :: Python :: 3.10
Classifier: Programming Language :: Python :: 3.11
Classifier: Programming Language :: Python :: 3.12
Classifier: Programming Language :: Python :: 3.13
